keep_awake/__init__.py
keep_awake/_native_api.cpython-314-darwin.so
keep_awake/_native_api.pyi
keep_awake/dbus_api.py
keep_awake/py.typed
keep_awake/py_module.c
keep_awake-1.1.2.dist-info/licenses/LICENSE
keep_awake-1.1.2.dist-info/METADATA
keep_awake-1.1.2.dist-info/WHEEL
keep_awake-1.1.2.dist-info/top_level.txt
keep_awake-1.1.2.dist-info/RECORD
