Metadata-Version: 2.4
Name: keep_awake
Version: 1.1.2
Summary: Prevent your computer from going to sleep.
Author-email: Kevin Chen <1354016594@qq.com>
License-Expression: MIT
Project-URL: Home-page, https://github.com/czf0613/keep_awake_py
Keywords: sleep,prevent,awake,idle
Classifier: Intended Audience :: Developers
Classifier: Operating System :: Microsoft :: Windows
Classifier: Operating System :: MacOS :: MacOS X
Classifier: Operating System :: POSIX :: Linux
Requires-Python: >=3.8
License-File: LICENSE
Provides-Extra: linux
Requires-Dist: dbus-python>=1.4.0; extra == "linux"
Dynamic: license-file
